<?xml version="1.0" encoding="UTF-8"?>
<!-- Created with TexturePacker http://www.codeandweb.com/texturepacker-->
<!-- $TexturePacker:SmartUpdate:446d8297c50c31df20f8612eca42e13e:4b1b353f335849d4ede53d776cb234c0:14e5c86b7d062cdab59613e79e6bb9e6$ -->
<TextureAtlas imagePath="gui.png" width="1024" height="2048">
    <SubTexture name="characters/00" x="468" y="1054" rotated="true" width="115" height="93" frameX="-21" frameY="0" frameWidth="131" frameHeight="131"/>
    <SubTexture name="characters/01" x="894" y="1152" width="103" height="88" frameX="-14" frameY="-25" frameWidth="131" frameHeight="131"/>
    <SubTexture name="characters/02" x="497" y="577" rotated="true" width="100" height="85" frameX="-23" frameY="-11" frameWidth="131" frameHeight="131"/>
    <SubTexture name="characters/03" x="879" y="1834" width="85" height="85" frameX="-23" frameY="-26" frameWidth="131" frameHeight="131"/>
    <SubTexture name="characters/04" x="894" y="1246" rotated="true" width="94" height="85" frameX="-23" frameY="-17" frameWidth="131" frameHeight="131"/>
    <SubTexture name="characters/05" x="783" y="1769" rotated="true" width="90" height="92" frameX="-16" frameY="-21" frameWidth="131" frameHeight="131"/>
    <SubTexture name="characters/06" x="792" y="1925" width="85" height="85" frameX="-23" frameY="-23" frameWidth="131" frameHeight="131"/>
    <SubTexture name="characters/07" x="466" y="1153" rotated="true" width="94" height="85" frameX="-23" frameY="-23" frameWidth="131" frameHeight="131"/>
    <SubTexture name="characters/08" x="879" y="1743" rotated="true" width="88" height="85" frameX="-23" frameY="-23" frameWidth="131" frameHeight="131"/>
    <SubTexture name="common/back" x="783" y="1731" rotated="true" width="27" height="32" frameX="0" frameY="-2" frameWidth="32" frameHeight="29"/>
    <SubTexture name="common/bar_active" x="525" y="311" width="15" height="15"/>
    <SubTexture name="common/bar_empty" x="525" y="332" width="15" height="15"/>
    <SubTexture name="common/coin" x="202" y="1604" width="52" height="50"/>
    <SubTexture name="common/navigate_big" x="446" y="1970" width="57" height="65"/>
    <SubTexture name="common/navigation" x="518" y="1743" width="35" height="41"/>
    <SubTexture name="common/pause" x="975" y="218" width="44" height="44"/>
    <SubTexture name="common/settings" x="975" y="268" width="44" height="44"/>
    <SubTexture name="episode_screen/maelstorm_episode" x="4" y="443" width="487" height="214" frameX="-39" frameY="-15" frameWidth="541" frameHeight="263"/>
    <SubTexture name="episode_screen/milkyway_episode" x="4" y="148" width="515" height="289" frameX="-5" frameY="-6" frameWidth="525" frameHeight="300"/>
    <SubTexture name="episode_screen/secret_episode" x="605" y="372" rotated="true" width="355" height="483" frameX="-7" frameY="-17" frameWidth="525" frameHeight="375"/>
    <SubTexture name="game_screen/fuel" x="168" y="1992" width="50" height="50"/>
    <SubTexture name="game_screen/fuel_index_full" x="497" y="443" rotated="true" width="22" height="128"/>
    <SubTexture name="game_screen/fuel_life_index_empty" x="525" y="148" rotated="true" width="21" height="128"/>
    <SubTexture name="game_screen/life" x="260" y="1743" width="50" height="50"/>
    <SubTexture name="game_screen/life_index_full" x="468" y="911" width="128" height="22"/>
    <SubTexture name="level_screen/arrow" x="552" y="193" width="49" height="49"/>
    <SubTexture name="level_screen/glow_active" x="383" y="1799" rotated="true" width="158" height="165" frameX="0" frameY="-3" frameWidth="165" frameHeight="165"/>
    <SubTexture name="level_screen/glow_active_circle" x="818" y="1337" width="202" height="202" frameX="-2" frameY="-2" frameWidth="206" frameHeight="206"/>
    <SubTexture name="level_screen/next_level" x="4" y="1799" rotated="true" width="185" height="187" frameX="0" frameY="-1" frameWidth="188" frameHeight="188"/>
    <SubTexture name="level_screen/next_level_symbol" x="468" y="939" rotated="true" width="118" height="109" frameX="-4" frameY="-1" frameWidth="113" frameHeight="120"/>
    <SubTexture name="level_screen/star_big" x="202" y="1660" width="52" height="50" frameX="-2" frameY="-3" frameWidth="56" frameHeight="56"/>
    <SubTexture name="level_screen/star_big_empty" x="202" y="1716" width="52" height="50" frameX="-2" frameY="-3" frameWidth="56" frameHeight="56"/>
    <SubTexture name="main_screen/achievements" x="291" y="1983" width="149" height="59"/>
    <SubTexture name="main_screen/achievements_teaser" x="4" y="1604" width="192" height="189"/>
    <SubTexture name="main_screen/choose_level" x="468" y="668" width="131" height="103"/>
    <SubTexture name="main_screen/choose_level_teaser" x="818" y="1545" width="194" height="192"/>
    <SubTexture name="main_screen/free_coins" x="966" y="643" rotated="true" width="53" height="113"/>
    <SubTexture name="main_screen/free_coins_teaser" x="622" y="1565" width="161" height="160" frameX="-1" frameY="0" frameWidth="162" frameHeight="160"/>
    <SubTexture name="main_screen/garage" x="913" y="1107" width="105" height="39"/>
    <SubTexture name="main_screen/garage_teaser" x="264" y="1514" width="205" height="203" frameX="-1" frameY="0" frameWidth="206" frameHeight="203"/>
    <SubTexture name="main_screen/glow" x="4" y="1123" width="279" height="278" frameX="-3" frameY="-4" frameWidth="285" frameHeight="282"/>
    <SubTexture name="main_screen/logo_adventure" x="602" y="861" width="328" height="98"/>
    <SubTexture name="main_screen/logo_kosmos" x="589" y="1130" width="299" height="179"/>
    <SubTexture name="main_screen/play_button" x="4" y="1407" width="254" height="191" frameX="-2" frameY="0" frameWidth="258" frameHeight="195"/>
    <SubTexture name="main_screen/play_button_en" x="552" y="88" rotated="true" width="49" height="99"/>
    <SubTexture name="main_screen/play_button_ru" x="975" y="4" rotated="true" width="44" height="156"/>
    <SubTexture name="main_screen/ray" x="4" y="88" width="542" height="54" frameX="-70" frameY="0" frameWidth="612" frameHeight="54"/>
    <SubTexture name="main_screen/ribbon" x="340" y="1799" rotated="true" width="37" height="169"/>
    <SubTexture name="main_screen/settings_button" x="966" y="762" rotated="true" width="52" height="146"/>
    <SubTexture name="main_screen/settings_icon" x="525" y="282" width="19" height="23"/>
    <SubTexture name="main_screen/ship_shadow" x="994" y="1246" rotated="true" width="25" height="38"/>
    <SubTexture name="pop_up/back" x="607" y="4" width="362" height="362"/>
    <SubTexture name="pop_up/button_big" x="695" y="1891" width="91" height="92"/>
    <SubTexture name="pop_up/button_close" x="525" y="542" width="26" height="28"/>
    <SubTexture name="pop_up/button_fb" x="525" y="471" rotated="true" width="66" height="65"/>
    <SubTexture name="pop_up/button_feedback" x="936" y="914" rotated="true" width="77" height="187"/>
    <SubTexture name="pop_up/button_first" x="552" y="248" rotated="true" width="47" height="159"/>
    <SubTexture name="pop_up/button_music_off" x="466" y="1244" width="36" height="47" frameX="0" frameY="0" frameWidth="36" frameHeight="50"/>
    <SubTexture name="pop_up/button_music_on" x="364" y="1743" width="36" height="50"/>
    <SubTexture name="pop_up/button_second" x="4" y="1992" width="158" height="50"/>
    <SubTexture name="pop_up/button_small" x="475" y="1514" width="77" height="77"/>
    <SubTexture name="pop_up/button_sound_off" x="316" y="1743" rotated="true" width="42" height="50" frameX="0" frameY="0" frameWidth="50" frameHeight="46"/>
    <SubTexture name="pop_up/button_sound_on" x="975" y="166" width="44" height="46" frameX="0" frameY="0" frameWidth="50" frameHeight="46"/>
    <SubTexture name="pop_up/button_vk" x="406" y="1723" width="65" height="66"/>
    <SubTexture name="pop_up/check" x="224" y="1983" width="61" height="61" frameX="0" frameY="0" frameWidth="61" frameHeight="65"/>
    <SubTexture name="pop_up/check_glow" x="477" y="1597" width="139" height="139" frameX="-2" frameY="-2" frameWidth="143" frameHeight="143"/>
    <SubTexture name="pop_up/cup" x="564" y="1315" rotated="true" width="248" height="244"/>
    <SubTexture name="pop_up/dialogue" x="4" y="4" width="597" height="78"/>
    <SubTexture name="pop_up/feedback_icon" x="936" y="861" rotated="true" width="23" height="38"/>
    <SubTexture name="pop_up/glow_button_01" x="468" y="777" width="128" height="128" frameX="-30" frameY="-30" frameWidth="188" frameHeight="188"/>
    <SubTexture name="pop_up/glow_button_02" x="547" y="1891" width="142" height="142" frameX="-23" frameY="-23" frameWidth="188" frameHeight="188"/>
    <SubTexture name="pop_up/glow_button_03" x="622" y="1731" rotated="true" width="155" height="154" frameX="-17" frameY="-16" frameWidth="188" frameHeight="188"/>
    <SubTexture name="pop_up/glow_button_04" x="289" y="1123" rotated="true" width="171" height="170" frameX="-9" frameY="-8" frameWidth="188" frameHeight="188"/>
    <SubTexture name="pop_up/glow_button_05" x="622" y="1731" rotated="true" width="155" height="154" frameX="-17" frameY="-16" frameWidth="188" frameHeight="188"/>
    <SubTexture name="pop_up/glow_button_06" x="547" y="1891" width="142" height="142" frameX="-23" frameY="-23" frameWidth="188" frameHeight="188"/>
    <SubTexture name="pop_up/level_done_glow" x="4" y="663" width="458" height="454" frameX="0" frameY="-2" frameWidth="458" frameHeight="458"/>
    <SubTexture name="pop_up/level_done_img" x="592" y="965" width="315" height="159"/>
    <SubTexture name="pop_up/line" x="975" y="318" rotated="true" width="43" height="319" frameX="-2" frameY="0" frameWidth="322" frameHeight="43"/>
    <SubTexture name="pop_up/menu" x="477" y="1743" rotated="true" width="35" height="43"/>
    <SubTexture name="pop_up/next" x="525" y="413" width="69" height="52"/>
    <SubTexture name="pop_up/replay" x="508" y="1244" rotated="true" width="50" height="43"/>
    <SubTexture name="pop_up/resume" x="557" y="542" rotated="true" width="42" height="27"/>
    <SubTexture name="pop_up/try_again_bottom" x="289" y="1299" width="269" height="209"/>
    <SubTexture name="pop_up/try_again_dust" x="195" y="1799" width="139" height="178" frameX="0" frameY="-10" frameWidth="139" frameHeight="188"/>
</TextureAtlas>
